crypto_data_ingestion/__init__.py
crypto_data_ingestion/api.py
crypto_data_ingestion/data_operations.py
crypto_data_ingestion/storage.py
crypto_data_ingestion/utils.py
crypto_data_ingestion-0.2.8.dist-info/METADATA
crypto_data_ingestion-0.2.8.dist-info/WHEEL
crypto_data_ingestion-0.2.8.dist-info/RECORD
